opentaxii/__init__.py
opentaxii/_version.py
opentaxii/config.py
opentaxii/defaults.yml
opentaxii/entities.py
opentaxii/exceptions.py
opentaxii/http.py
opentaxii/local.py
opentaxii/management.py
opentaxii/middleware.py
opentaxii/server.py
opentaxii/signals.py
opentaxii/sqldb_helper.py
opentaxii/utils.py
opentaxii/auth/__init__.py
opentaxii/auth/api.py
opentaxii/auth/manager.py
opentaxii/auth/sqldb/__init__.py
opentaxii/auth/sqldb/api.py
opentaxii/auth/sqldb/models.py
opentaxii/cli/__init__.py
opentaxii/cli/auth.py
opentaxii/cli/persistence.py
opentaxii/cli/run.py
opentaxii/common/__init__.py
opentaxii/common/entities.py
opentaxii/common/sqldb.py
opentaxii/persistence/__init__.py
opentaxii/persistence/api.py
opentaxii/persistence/exceptions.py
opentaxii/persistence/manager.py
opentaxii/persistence/sqldb/__init__.py
opentaxii/persistence/sqldb/api.py
opentaxii/persistence/sqldb/common.py
opentaxii/persistence/sqldb/converters.py
opentaxii/persistence/sqldb/models.py
opentaxii/persistence/sqldb/taxii2models.py
opentaxii/taxii/__init__.py
opentaxii/taxii/bindings.py
opentaxii/taxii/converters.py
opentaxii/taxii/entities.py
opentaxii/taxii/exceptions.py
opentaxii/taxii/http.py
opentaxii/taxii/status.py
opentaxii/taxii/utils.py
opentaxii/taxii/services/__init__.py
opentaxii/taxii/services/abstract.py
opentaxii/taxii/services/collection_management.py
opentaxii/taxii/services/discovery.py
opentaxii/taxii/services/inbox.py
opentaxii/taxii/services/poll.py
opentaxii/taxii/services/handlers/__init__.py
opentaxii/taxii/services/handlers/base_handlers.py
opentaxii/taxii/services/handlers/collection_information_request_handlers.py
opentaxii/taxii/services/handlers/discovery_request_handlers.py
opentaxii/taxii/services/handlers/inbox_message_handlers.py
opentaxii/taxii/services/handlers/poll_fulfilment_request_handlers.py
opentaxii/taxii/services/handlers/poll_request_handlers.py
opentaxii/taxii/services/handlers/subscription_request_handlers.py
opentaxii/taxii2/__init__.py
opentaxii-0.9.3.dist-info/LICENSE.rst
opentaxii-0.9.3.dist-info/METADATA
opentaxii-0.9.3.dist-info/WHEEL
opentaxii-0.9.3.dist-info/entry_points.txt
opentaxii-0.9.3.dist-info/top_level.txt
opentaxii-0.9.3.dist-info/RECORD
