Metadata-Version: 2.1
Name: opentaxii
Version: 0.9.3
Summary: TAXII server implementation in Python from EclecticIQ
Home-page: https://github.com/EclecticIQ/OpenTAXII
Author: EclecticIQ
Author-email: opentaxii@eclecticiq.com
License: BSD License
Classifier: Development Status :: 4 - Beta
Classifier: Intended Audience :: Developers
Classifier: Intended Audience :: Information Technology
Classifier: License :: OSI Approved :: BSD License
Classifier: Programming Language :: Python
Classifier: Programming Language :: Python :: 3.6
Classifier: Programming Language :: Python :: 3.7
Classifier: Programming Language :: Python :: 3.8
Classifier: Programming Language :: Python :: 3.9
Classifier: Programming Language :: Python :: 3.10
Classifier: Programming Language :: Python :: Implementation :: PyPy
Classifier: Topic :: Internet
Classifier: Topic :: Security
Classifier: Topic :: Internet :: WWW/HTTP :: Dynamic Content
Classifier: Topic :: Software Development :: Libraries :: Python Modules
License-File: LICENSE.rst
Requires-Dist: pytz (>=2017.2)
Requires-Dist: libtaxii (>=1.1.111)
Requires-Dist: lxml (>=4.3.1)
Requires-Dist: pyyaml (>=3.11)
Requires-Dist: flask (>=0.10.1)
Requires-Dist: sqlalchemy (>=1.1.2)
Requires-Dist: structlog (>=18.1.0)
Requires-Dist: blinker (>=1.4)
Requires-Dist: pyjwt (>=1.4.0)
Requires-Dist: six (>=1.10.0)
Requires-Dist: mypy-extensions (>=0.4.3)
Requires-Dist: stix2 (>=3.0.1)
Requires-Dist: marshmallow (>=3.10.0)
